communitysdk/__init__.py
communitysdk/devicemanager.py
communitysdk/motionsensorkit.py
communitysdk/retailpixelkit.py
communitysdk/rpcclient.py
communitysdk/serialdevice.py
kano_community_sdk-0.2.0.dist-info/AUTHORS.rst
kano_community_sdk-0.2.0.dist-info/LICENSE
kano_community_sdk-0.2.0.dist-info/METADATA
kano_community_sdk-0.2.0.dist-info/WHEEL
kano_community_sdk-0.2.0.dist-info/top_level.txt
kano_community_sdk-0.2.0.dist-info/RECORD
